culturovaultapi/__init__.py
culturovaultapi/cli.py
culturovaultapi/uploader.py
culturovaultapi/viewer.py
culturovault-0.0.1.dist-info/METADATA
culturovault-0.0.1.dist-info/WHEEL
culturovault-0.0.1.dist-info/top_level.txt
culturovault-0.0.1.dist-info/RECORD
