Metadata-Version: 2.4
Name: culturovault
Version: 0.0.1
Summary: An API for CulturoVault project
Home-page: https://culturovaultignicion.pythonanywhere.com/
Author: D. Saahishnu Ram
Author-email: Saahishnu Ram <elsa371123@outlook.com>
License: MIT
Requires-Python: >=3.7
Requires-Dist: flask
Requires-Dist: selenium
Dynamic: author
Dynamic: home-page
Dynamic: requires-python
